{
  "fiscal_year": 2019,
  "is_current_year": false,
  "available_months": [
    "Nov",
    "Dec",
    "Mar",
    "Apr",
    "May",
    "Jun",
    "Jul",
    "Aug",
    "Sep"
  ],
  "missing_months": [
    "Oct",
    "Jan",
    "Feb"
  ],
  "quarter_mapping": {
    "Q1": [
      "Oct",
      "Nov",
      "Dec"
    ],
    "Q2": [
      "Jan",
      "Feb",
      "Mar"
    ],
    "Q3": [
      "Apr",
      "May",
      "Jun"
    ],
    "Q4": [
      "Jul",
      "Aug",
      "Sep"
    ]
  },
  "quarter_data": {},
  "total_agencies": 29,
  "total_rows": 140304,
  "processed_date": "2025-10-30T20:25:59.800082",
  "data_file": "sf133_2019_master.csv",
  "validation_passed": true,
  "tafs_coverage": {
    "validation_passed": true,
    "has_coverage_issues": true,
    "overall_coverage_percent": 46.83698296836983,
    "baseline_total_accounts": 9042,
    "current_total_accounts": 4235,
    "agency_coverage": {
      "400 Years of African-American History Commission": {
        "baseline_accounts": 711,
        "current_accounts": 0,
        "coverage_percent": 0.0
      },
      "Corps of Engineers-Civil Works": {
        "baseline_accounts": 54,
        "current_accounts": 37,
        "coverage_percent": 68.51851851851852
      },
      "Department of Agriculture": {
        "baseline_accounts": 812,
        "current_accounts": 326,
        "coverage_percent": 40.14778325123153
      },
      "Department of Commerce": {
        "baseline_accounts": 220,
        "current_accounts": 113,
        "coverage_percent": 51.36363636363637
      },
      "Department of Defense-Military": {
        "baseline_accounts": 874,
        "current_accounts": 428,
        "coverage_percent": 48.970251716247134
      },
      "Department of Education": {
        "baseline_accounts": 270,
        "current_accounts": 130,
        "coverage_percent": 48.148148148148145
      },
      "Department of Energy": {
        "baseline_accounts": 264,
        "current_accounts": 111,
        "coverage_percent": 42.04545454545455
      },
      "Department of Health and Human Services": {
        "baseline_accounts": 997,
        "current_accounts": 263,
        "coverage_percent": 26.37913741223671
      },
      "Department of Homeland Security": {
        "baseline_accounts": 594,
        "current_accounts": 279,
        "coverage_percent": 46.96969696969697
      },
      "Department of Housing and Urban Development": {
        "baseline_accounts": 299,
        "current_accounts": 192,
        "coverage_percent": 64.21404682274247
      },
      "Department of Justice": {
        "baseline_accounts": 215,
        "current_accounts": 133,
        "coverage_percent": 61.86046511627907
      },
      "Department of Labor": {
        "baseline_accounts": 251,
        "current_accounts": 120,
        "coverage_percent": 47.808764940239044
      },
      "Department of State": {
        "baseline_accounts": 305,
        "current_accounts": 141,
        "coverage_percent": 46.22950819672131
      },
      "Department of Transportation": {
        "baseline_accounts": 460,
        "current_accounts": 228,
        "coverage_percent": 49.56521739130435
      },
      "Department of Veterans Affairs": {
        "baseline_accounts": 256,
        "current_accounts": 106,
        "coverage_percent": 41.40625
      },
      "Department of the Interior": {
        "baseline_accounts": 452,
        "current_accounts": 239,
        "coverage_percent": 52.876106194690266
      },
      "Department of the Treasury": {
        "baseline_accounts": 316,
        "current_accounts": 156,
        "coverage_percent": 49.36708860759494
      },
      "Environmental Protection Agency": {
        "baseline_accounts": 79,
        "current_accounts": 38,
        "coverage_percent": 48.10126582278481
      },
      "Executive Office of the President": {
        "baseline_accounts": 161,
        "current_accounts": 74,
        "coverage_percent": 45.962732919254655
      },
      "General Services Administration": {
        "baseline_accounts": 82,
        "current_accounts": 54,
        "coverage_percent": 65.85365853658537
      },
      "International Assistance Programs": {
        "baseline_accounts": 581,
        "current_accounts": 245,
        "coverage_percent": 42.168674698795186
      },
      "Judicial Branch": {
        "baseline_accounts": 69,
        "current_accounts": 45,
        "coverage_percent": 65.21739130434783
      },
      "Legislative Branch": {
        "baseline_accounts": 356,
        "current_accounts": 160,
        "coverage_percent": 44.9438202247191
      },
      "National Aeronautics and Space Administration": {
        "baseline_accounts": 125,
        "current_accounts": 56,
        "coverage_percent": 44.800000000000004
      },
      "National Science Foundation": {
        "baseline_accounts": 52,
        "current_accounts": 24,
        "coverage_percent": 46.15384615384615
      },
      "Office of Personnel Management": {
        "baseline_accounts": 36,
        "current_accounts": 17,
        "coverage_percent": 47.22222222222222
      },
      "Other Defense Civil Programs": {
        "baseline_accounts": 46,
        "current_accounts": 29,
        "coverage_percent": 63.04347826086957
      },
      "Small Business Administration": {
        "baseline_accounts": 57,
        "current_accounts": 26,
        "coverage_percent": 45.614035087719294
      },
      "Social Security Administration": {
        "baseline_accounts": 48,
        "current_accounts": 24,
        "coverage_percent": 50.0
      }
    },
    "agencies_below_threshold": [
      "400 Years of African-American History Commission: 0.0%",
      "Corps of Engineers-Civil Works: 68.5%",
      "Department of Agriculture: 40.1%",
      "Department of Commerce: 51.4%",
      "Department of Defense-Military: 49.0%",
      "Department of Education: 48.1%",
      "Department of Energy: 42.0%",
      "Department of Health and Human Services: 26.4%",
      "Department of Homeland Security: 47.0%",
      "Department of Housing and Urban Development: 64.2%",
      "Department of Justice: 61.9%",
      "Department of Labor: 47.8%",
      "Department of State: 46.2%",
      "Department of Transportation: 49.6%",
      "Department of Veterans Affairs: 41.4%",
      "Department of the Interior: 52.9%",
      "Department of the Treasury: 49.4%",
      "Environmental Protection Agency: 48.1%",
      "Executive Office of the President: 46.0%",
      "General Services Administration: 65.9%",
      "International Assistance Programs: 42.2%",
      "Judicial Branch: 65.2%",
      "Legislative Branch: 44.9%",
      "National Aeronautics and Space Administration: 44.8%",
      "National Science Foundation: 46.2%",
      "Office of Personnel Management: 47.2%",
      "Other Defense Civil Programs: 63.0%",
      "Small Business Administration: 45.6%",
      "Social Security Administration: 50.0%"
    ],
    "threshold_percent": 80.0
  }
}